pgtracer/__init__.py
pgtracer/utils.py
pgtracer/ebpf/__init__.py
pgtracer/ebpf/collector.py
pgtracer/ebpf/dwarf.py
pgtracer/ebpf/eh_frame_hdr.py
pgtracer/ebpf/guc.py
pgtracer/ebpf/unwind.py
pgtracer/ebpf/code/block_rq.c
pgtracer/ebpf/code/data.h
pgtracer/ebpf/code/ebpf_maps.h
pgtracer/ebpf/code/gucset.c
pgtracer/ebpf/code/perf.c
pgtracer/ebpf/code/plan.c
pgtracer/ebpf/code/program.c
pgtracer/ebpf/code/stack.h
pgtracer/ebpf/code/utils.h
pgtracer/model/__init__.py
pgtracer/model/plan.py
pgtracer/model/query.py
pgtracer/scripts/pgtrace_gucs.py
pgtracer/scripts/pgtrace_queries.py
pgtracer-0.1.0.dist-info/LICENSE
pgtracer-0.1.0.dist-info/METADATA
pgtracer-0.1.0.dist-info/WHEEL
pgtracer-0.1.0.dist-info/entry_points.txt
pgtracer-0.1.0.dist-info/top_level.txt
pgtracer-0.1.0.dist-info/RECORD
