Metadata-Version: 2.1
Name: pgtracer
Version: 0.1.0
Summary: Tracing tools for PostgreSQL
Author-email: Ronan Dunklau <ronan.dunklau@aiven.com>
Classifier: Programming Language :: Python :: 3
Classifier: License :: OSI Approved :: PostgreSQL License
Classifier: Operating System :: POSIX :: Linux
Requires-Python: >=3.7
License-File: LICENSE
Requires-Dist: pyelftools
Requires-Dist: pypsutil
Provides-Extra: lint
Requires-Dist: black ; extra == 'lint'
Requires-Dist: isort ; extra == 'lint'
Requires-Dist: mypy ; extra == 'lint'
Requires-Dist: pylint ; extra == 'lint'
Requires-Dist: pylint-exit ; extra == 'lint'
Provides-Extra: test
Requires-Dist: psycopg ; extra == 'test'
Requires-Dist: pytest ; extra == 'test'
Requires-Dist: pytest-coverage ; extra == 'test'
Requires-Dist: pytest-postgresql ; extra == 'test'
Requires-Dist: flaky ; extra == 'test'
